{
  "localizedName": "Chasing house",
  "title": "Soñar con Chasing house",
  "seoDescription": "Significado de Chasing house en los sueños.",
  "introduction": "Soñar con **Chasing house** es un mensaje de tu subconsciente. Simboliza **Meaning not found**.",
  "symbolism": "El símbolo **Chasing house** conecta tu consciente con tu inconsciente.",
  "cosmicAnalysis": "Los sueños de Chasing house están profundamente conectados con el ciclo lunar. Durante la **Luna Creciente**, este símbolo sugiere crecimiento.",
  "commonScenarios": [
    "**Ver un Chasing house:** Una señal importante."
  ],
  "cta": "Descarga **Dream Boat** para más."
}