{
  "localizedName": "Red key",
  "title": "Soñar con Red key",
  "seoDescription": "Significado de Red key en los sueños.",
  "introduction": "Soñar con **Red key** es un mensaje de tu subconsciente. Simboliza **Meaning not found**.",
  "symbolism": "El símbolo **Red key** conecta tu consciente con tu inconsciente.",
  "cosmicAnalysis": "Los sueños de Red key están profundamente conectados con el ciclo lunar. Durante la **Luna Creciente**, este símbolo sugiere crecimiento.",
  "commonScenarios": [
    "**Ver un Red key:** Una señal importante."
  ],
  "cta": "Descarga **Dream Boat** para más."
}