{
  "localizedName": "Alley",
  "title": "Traumdeutung Alley",
  "seoDescription": "Bedeutung von Alley im Traum.",
  "introduction": "Ein Traum von **Alley** ist eine Botschaft Ihres Unterbewusstseins. Es symbolisiert **SHADOWY SHORTCUT**.",
  "symbolism": "Das Symbol **Alley** verbindet Ihr Bewusstsein mit dem Unbewussten.",
  "cosmicAnalysis": "Träume von Alley sind tief mit dem Mondzyklus verbunden. Während des **Zunehmenden Mondes** deutet dieses Symbol auf Wachstum hin.",
  "commonScenarios": [
    "**Alley sehen:** Ein wichtiges Zeichen."
  ],
  "cta": "Laden Sie **Dream Boat** herunter für mehr."
}