{
  "localizedName": "Barn",
  "title": "Traumdeutung Barn",
  "seoDescription": "Bedeutung von Barn im Traum.",
  "introduction": "Ein Traum von **Barn** ist eine Botschaft Ihres Unterbewusstseins. Es symbolisiert **PLACE OF NOURISHMENT / INSTINCT**.",
  "symbolism": "Das Symbol **Barn** verbindet Ihr Bewusstsein mit dem Unbewussten.",
  "cosmicAnalysis": "Träume von Barn sind tief mit dem Mondzyklus verbunden. Während des **Zunehmenden Mondes** deutet dieses Symbol auf Wachstum hin.",
  "commonScenarios": [
    "**Barn sehen:** Ein wichtiges Zeichen."
  ],
  "cta": "Laden Sie **Dream Boat** herunter für mehr."
}