{
  "localizedName": "Captain",
  "title": "Traumdeutung Captain",
  "seoDescription": "Bedeutung von Captain im Traum.",
  "introduction": "Ein Traum von **Captain** ist eine Botschaft Ihres Unterbewusstseins. Es symbolisiert **DIRECTOR OF DESTINY**.",
  "symbolism": "Das Symbol **Captain** verbindet Ihr Bewusstsein mit dem Unbewussten.",
  "cosmicAnalysis": "Träume von Captain sind tief mit dem Mondzyklus verbunden. Während des **Zunehmenden Mondes** deutet dieses Symbol auf Wachstum hin.",
  "commonScenarios": [
    "**Captain sehen:** Ein wichtiges Zeichen."
  ],
  "cta": "Laden Sie **Dream Boat** herunter für mehr."
}