{
  "localizedName": "Car",
  "title": "Traumdeutung Car",
  "seoDescription": "Bedeutung von Car im Traum.",
  "introduction": "Ein Traum von **Car** ist eine Botschaft Ihres Unterbewusstseins. Es symbolisiert **EGO DRIVE**.",
  "symbolism": "Das Symbol **Car** verbindet Ihr Bewusstsein mit dem Unbewussten.",
  "cosmicAnalysis": "Träume von Car sind tief mit dem Mondzyklus verbunden. Während des **Zunehmenden Mondes** deutet dieses Symbol auf Wachstum hin.",
  "commonScenarios": [
    "**Car sehen:** Ein wichtiges Zeichen."
  ],
  "cta": "Laden Sie **Dream Boat** herunter für mehr."
}