{
  "title": "Tote Drache im Traum: Bedeutung & Interpretation",
  "seoDescription": "Entdecken Sie, was es bedeutet, von einer toteen drache zu träumen. Jung'sche Analyse von tote drache Träumen.",
  "introduction": "Wenn eine drache in Ihren Träumen erscheint, gefärbt durch die Qualität \"tote\", wird ihre Botschaft spezifischer und dringender.",
  "symbolism": "Die tote Qualität fügt der Kernsymbolik der drache, die the devouring mother / chaos repräsentiert, die Dimension von Enden, Transformation oder Loslassen hinzu.\n\nDiese Kombination deutet darauf hin, dass Ihre Psyche etwas mit sowohl der archetypischen Energie der drache ALS AUCH der emotionalen Ladung von \"tote\" verarbeitet.",
  "cosmicAnalysis": "Tote Drache Träume sind während bestimmter Mondphasen besonders kraftvoll. Ein Vollmond verstärkt die emotionale Intensität, während ein Neumond darauf hindeutet, dass dieses Symbol zum ersten Mal aus Ihrem tiefen Unbewussten auftaucht.",
  "commonScenarios": [
    "Eine tote drache, die sich Ihnen nähert - Konfrontation mit dieser Energie steht bevor",
    "Mehrere tote dracheen - die Botschaft wird zur Betonung wiederholt",
    "Sich in eine tote drache verwandeln - Sie integrieren diesen Archetyp",
    "Vor einer toteen drache weglaufen - Vermeidung dieses Aspekts von sich selbst"
  ],
  "cta": "Jedes Traumsymbol trägt persönliche Bedeutung. Verfolgen Sie Ihre tote drache Träume, um tiefere Muster zu entdecken."
}