{
  "localizedName": "Dead baby",
  "title": "Traumdeutung Dead baby",
  "seoDescription": "Bedeutung von Dead baby im Traum.",
  "introduction": "Ein Traum von **Dead baby** ist eine Botschaft Ihres Unterbewusstseins. Es symbolisiert **Meaning not found**.",
  "symbolism": "Das Symbol **Dead baby** verbindet Ihr Bewusstsein mit dem Unbewussten.",
  "cosmicAnalysis": "Träume von Dead baby sind tief mit dem Mondzyklus verbunden. Während des **Zunehmenden Mondes** deutet dieses Symbol auf Wachstum hin.",
  "commonScenarios": [
    "**Dead baby sehen:** Ein wichtiges Zeichen."
  ],
  "cta": "Laden Sie **Dream Boat** herunter für mehr."
}