{
  "localizedName": "Death",
  "title": "Traumdeutung Death",
  "seoDescription": "Bedeutung von Death im Traum.",
  "introduction": "Ein Traum von **Death** ist eine Botschaft Ihres Unterbewusstseins. Es symbolisiert **TRANSFORMATION**.",
  "symbolism": "Das Symbol **Death** verbindet Ihr Bewusstsein mit dem Unbewussten.",
  "cosmicAnalysis": "Träume von Death sind tief mit dem Mondzyklus verbunden. Während des **Zunehmenden Mondes** deutet dieses Symbol auf Wachstum hin.",
  "commonScenarios": [
    "**Death sehen:** Ein wichtiges Zeichen."
  ],
  "cta": "Laden Sie **Dream Boat** herunter für mehr."
}