{
  "title": "Riesige SNOW im Traum: Bedeutung & Interpretation",
  "seoDescription": "Entdecken Sie, was es bedeutet, von einer riesigeen snow zu träumen. Jung'sche Analyse von riesige snow Träumen.",
  "introduction": "Wenn eine snow in Ihren Träumen erscheint, gefärbt durch die Qualität \"riesige\", wird ihre Botschaft spezifischer und dringender.",
  "symbolism": "Die riesige Qualität fügt der Kernsymbolik der snow, die emotional numbness repräsentiert, die Dimension von überwältigende Gefühle oder aufgeblähte Bedeutung hinzu.\n\nDiese Kombination deutet darauf hin, dass Ihre Psyche etwas mit sowohl der archetypischen Energie der snow ALS AUCH der emotionalen Ladung von \"riesige\" verarbeitet.",
  "cosmicAnalysis": "Riesige SNOW Träume sind während bestimmter Mondphasen besonders kraftvoll. Ein Vollmond verstärkt die emotionale Intensität, während ein Neumond darauf hindeutet, dass dieses Symbol zum ersten Mal aus Ihrem tiefen Unbewussten auftaucht.",
  "commonScenarios": [
    "Eine riesige snow, die sich Ihnen nähert - Konfrontation mit dieser Energie steht bevor",
    "Mehrere riesige snowen - die Botschaft wird zur Betonung wiederholt",
    "Sich in eine riesige snow verwandeln - Sie integrieren diesen Archetyp",
    "Vor einer riesigeen snow weglaufen - Vermeidung dieses Aspekts von sich selbst"
  ],
  "cta": "Jedes Traumsymbol trägt persönliche Bedeutung. Verfolgen Sie Ihre riesige snow Träume, um tiefere Muster zu entdecken."
}