{
  "localizedName": "Ice cream",
  "title": "Traumdeutung Ice cream",
  "seoDescription": "Bedeutung von Ice cream im Traum.",
  "introduction": "Ein Traum von **Ice cream** ist eine Botschaft Ihres Unterbewusstseins. Es symbolisiert **FLEETING PLEASURE**.",
  "symbolism": "Das Symbol **Ice cream** verbindet Ihr Bewusstsein mit dem Unbewussten.",
  "cosmicAnalysis": "Träume von Ice cream sind tief mit dem Mondzyklus verbunden. Während des **Zunehmenden Mondes** deutet dieses Symbol auf Wachstum hin.",
  "commonScenarios": [
    "**Ice cream sehen:** Ein wichtiges Zeichen."
  ],
  "cta": "Laden Sie **Dream Boat** herunter für mehr."
}