{
  "localizedName": "Moose",
  "title": "Traumdeutung Moose",
  "seoDescription": "Bedeutung von Moose im Traum.",
  "introduction": "Ein Traum von **Moose** ist eine Botschaft Ihres Unterbewusstseins. Es symbolisiert **INDIVIDUAL STRENGTH**.",
  "symbolism": "Das Symbol **Moose** verbindet Ihr Bewusstsein mit dem Unbewussten.",
  "cosmicAnalysis": "Träume von Moose sind tief mit dem Mondzyklus verbunden. Während des **Zunehmenden Mondes** deutet dieses Symbol auf Wachstum hin.",
  "commonScenarios": [
    "**Moose sehen:** Ein wichtiges Zeichen."
  ],
  "cta": "Laden Sie **Dream Boat** herunter für mehr."
}