{
  "title": "Traumdeutung Password",
  "seoDescription": "Bedeutung von Password im Traum.",
  "introduction": "Ein Traum von **Password** ist eine Botschaft Ihres Unterbewusstseins. Es symbolisiert **ACCESS TO HIDDEN KNOWLEDGE**.",
  "symbolism": "Das Symbol **Password** verbindet Ihr Bewusstsein mit dem Unbewussten.",
  "cosmicAnalysis": "Träume von Password sind tief mit dem Mondzyklus verbunden. Während des **Zunehmenden Mondes** deutet dieses Symbol auf Wachstum hin.",
  "commonScenarios": [
    "**Password sehen:** Ein wichtiges Zeichen."
  ],
  "cta": "Laden Sie **Dream Boat** herunter für mehr."
}