{
  "localizedName": "Red running",
  "title": "Traumdeutung Red running",
  "seoDescription": "Bedeutung von Red running im Traum.",
  "introduction": "Ein Traum von **Red running** ist eine Botschaft Ihres Unterbewusstseins. Es symbolisiert **Meaning not found**.",
  "symbolism": "Das Symbol **Red running** verbindet Ihr Bewusstsein mit dem Unbewussten.",
  "cosmicAnalysis": "Träume von Red running sind tief mit dem Mondzyklus verbunden. Während des **Zunehmenden Mondes** deutet dieses Symbol auf Wachstum hin.",
  "commonScenarios": [
    "**Red running sehen:** Ein wichtiges Zeichen."
  ],
  "cta": "Laden Sie **Dream Boat** herunter für mehr."
}