{
  "localizedName": "Bathtub",
  "title": "Sonhar com Bathtub",
  "seoDescription": "Significado de Bathtub nos sonhos.",
  "introduction": "Sonhar com **Bathtub** é uma mensagem do seu subconsciente. Simboliza **REGRESSION TO WOMB**.",
  "symbolism": "O símbolo **Bathtub** conecta seu consciente com o inconsciente.",
  "cosmicAnalysis": "Sonhos com Bathtub estão profundamente ligados ao ciclo lunar. Durante a **Lua Crescente**, este símbolo sugere crescimento.",
  "commonScenarios": [
    "**Ver um Bathtub:** Um sinal importante."
  ],
  "cta": "Baixe **Dream Boat** para mais."
}