{
  "localizedName": "Chasing snow",
  "title": "Sonhar com Chasing snow",
  "seoDescription": "Significado de Chasing snow nos sonhos.",
  "introduction": "Sonhar com **Chasing snow** é uma mensagem do seu subconsciente. Simboliza **Meaning not found**.",
  "symbolism": "O símbolo **Chasing snow** conecta seu consciente com o inconsciente.",
  "cosmicAnalysis": "Sonhos com Chasing snow estão profundamente ligados ao ciclo lunar. Durante a **Lua Crescente**, este símbolo sugere crescimento.",
  "commonScenarios": [
    "**Ver um Chasing snow:** Um sinal importante."
  ],
  "cta": "Baixe **Dream Boat** para mais."
}