{
  "localizedName": "Darkness",
  "title": "Sonhar com Darkness",
  "seoDescription": "Significado de Darkness nos sonhos.",
  "introduction": "Sonhar com **Darkness** é uma mensagem do seu subconsciente. Simboliza **THE UNCONSCIOUS**.",
  "symbolism": "O símbolo **Darkness** conecta seu consciente com o inconsciente.",
  "cosmicAnalysis": "Sonhos com Darkness estão profundamente ligados ao ciclo lunar. Durante a **Lua Crescente**, este símbolo sugere crescimento.",
  "commonScenarios": [
    "**Ver um Darkness:** Um sinal importante."
  ],
  "cta": "Baixe **Dream Boat** para mais."
}