{
  "localizedName": "Letter",
  "title": "Sonhar com Letter",
  "seoDescription": "Significado de Letter nos sonhos.",
  "introduction": "Sonhar com **Letter** é uma mensagem do seu subconsciente. Simboliza **MESSAGE FROM UNCONSCIOUS**.",
  "symbolism": "O símbolo **Letter** conecta seu consciente com o inconsciente.",
  "cosmicAnalysis": "Sonhos com Letter estão profundamente ligados ao ciclo lunar. Durante a **Lua Crescente**, este símbolo sugere crescimento.",
  "commonScenarios": [
    "**Ver um Letter:** Um sinal importante."
  ],
  "cta": "Baixe **Dream Boat** para mais."
}