{
  "localizedName": "Memory",
  "title": "Sonhar com Memory",
  "seoDescription": "Significado de Memory nos sonhos.",
  "introduction": "Sonhar com **Memory** é uma mensagem do seu subconsciente. Simboliza **PAST IMPRESSION**.",
  "symbolism": "O símbolo **Memory** conecta seu consciente com o inconsciente.",
  "cosmicAnalysis": "Sonhos com Memory estão profundamente ligados ao ciclo lunar. Durante a **Lua Crescente**, este símbolo sugere crescimento.",
  "commonScenarios": [
    "**Ver um Memory:** Um sinal importante."
  ],
  "cta": "Baixe **Dream Boat** para mais."
}