{
  "localizedName": "Owl",
  "title": "Sonhar com Owl",
  "seoDescription": "Significado de Owl nos sonhos.",
  "introduction": "Sonhar com **Owl** é uma mensagem do seu subconsciente. Simboliza **WISDOM IN DARKNESS**.",
  "symbolism": "O símbolo **Owl** conecta seu consciente com o inconsciente.",
  "cosmicAnalysis": "Sonhos com Owl estão profundamente ligados ao ciclo lunar. Durante a **Lua Crescente**, este símbolo sugere crescimento.",
  "commonScenarios": [
    "**Ver um Owl:** Um sinal importante."
  ],
  "cta": "Baixe **Dream Boat** para mais."
}