{
  "localizedName": "Red wolf",
  "title": "Sonhar com Red wolf",
  "seoDescription": "Significado de Red wolf nos sonhos.",
  "introduction": "Sonhar com **Red wolf** é uma mensagem do seu subconsciente. Simboliza **Meaning not found**.",
  "symbolism": "O símbolo **Red wolf** conecta seu consciente com o inconsciente.",
  "cosmicAnalysis": "Sonhos com Red wolf estão profundamente ligados ao ciclo lunar. Durante a **Lua Crescente**, este símbolo sugere crescimento.",
  "commonScenarios": [
    "**Ver um Red wolf:** Um sinal importante."
  ],
  "cta": "Baixe **Dream Boat** para mais."
}