{
  "localizedName": "Road",
  "title": "Sonhar com Road",
  "seoDescription": "Significado de Road nos sonhos.",
  "introduction": "Sonhar com **Road** é uma mensagem do seu subconsciente. Simboliza **THE LIFE PATH**.",
  "symbolism": "O símbolo **Road** conecta seu consciente com o inconsciente.",
  "cosmicAnalysis": "Sonhos com Road estão profundamente ligados ao ciclo lunar. Durante a **Lua Crescente**, este símbolo sugere crescimento.",
  "commonScenarios": [
    "**Ver um Road:** Um sinal importante."
  ],
  "cta": "Baixe **Dream Boat** para mais."
}