{
  "title": "Sonhar com Skin",
  "seoDescription": "Significado de Skin nos sonhos.",
  "introduction": "Sonhar com **Skin** é uma mensagem do seu subconsciente. Simboliza **BOUNDARY OF EGO**.",
  "symbolism": "O símbolo **Skin** conecta seu consciente com o inconsciente.",
  "cosmicAnalysis": "Sonhos com Skin estão profundamente ligados ao ciclo lunar. Durante a **Lua Crescente**, este símbolo sugere crescimento.",
  "commonScenarios": [
    "**Ver um Skin:** Um sinal importante."
  ],
  "cta": "Baixe **Dream Boat** para mais."
}