{
  "localizedName": "Stove",
  "title": "Sonhar com Stove",
  "seoDescription": "Significado de Stove nos sonhos.",
  "introduction": "Sonhar com **Stove** é uma mensagem do seu subconsciente. Simboliza **SOURCE OF ENERGY**.",
  "symbolism": "O símbolo **Stove** conecta seu consciente com o inconsciente.",
  "cosmicAnalysis": "Sonhos com Stove estão profundamente ligados ao ciclo lunar. Durante a **Lua Crescente**, este símbolo sugere crescimento.",
  "commonScenarios": [
    "**Ver um Stove:** Um sinal importante."
  ],
  "cta": "Baixe **Dream Boat** para mais."
}