{
  "title": "Sonhar com Sugar",
  "seoDescription": "Significado de Sugar nos sonhos.",
  "introduction": "Sonhar com **Sugar** é uma mensagem do seu subconsciente. Simboliza **SUPERFICIAL PLEASURE**.",
  "symbolism": "O símbolo **Sugar** conecta seu consciente com o inconsciente.",
  "cosmicAnalysis": "Sonhos com Sugar estão profundamente ligados ao ciclo lunar. Durante a **Lua Crescente**, este símbolo sugere crescimento.",
  "commonScenarios": [
    "**Ver um Sugar:** Um sinal importante."
  ],
  "cta": "Baixe **Dream Boat** para mais."
}