{
  "title": "Sonhar com Throat",
  "seoDescription": "Significado de Throat nos sonhos.",
  "introduction": "Sonhar com **Throat** é uma mensagem do seu subconsciente. Simboliza **EXPRESSIVE CHANNEL**.",
  "symbolism": "O símbolo **Throat** conecta seu consciente com o inconsciente.",
  "cosmicAnalysis": "Sonhos com Throat estão profundamente ligados ao ciclo lunar. Durante a **Lua Crescente**, este símbolo sugere crescimento.",
  "commonScenarios": [
    "**Ver um Throat:** Um sinal importante."
  ],
  "cta": "Baixe **Dream Boat** para mais."
}