{
  "title": "Sonhar com Turquoise",
  "seoDescription": "Significado de Turquoise nos sonhos.",
  "introduction": "Sonhar com **Turquoise** é uma mensagem do seu subconsciente. Simboliza **HEALING ENERGY**.",
  "symbolism": "O símbolo **Turquoise** conecta seu consciente com o inconsciente.",
  "cosmicAnalysis": "Sonhos com Turquoise estão profundamente ligados ao ciclo lunar. Durante a **Lua Crescente**, este símbolo sugere crescimento.",
  "commonScenarios": [
    "**Ver um Turquoise:** Um sinal importante."
  ],
  "cta": "Baixe **Dream Boat** para mais."
}