{
  "localizedName": "Wolf",
  "title": "Sonhar com Wolf",
  "seoDescription": "Significado de Wolf nos sonhos.",
  "introduction": "Sonhar com **Wolf** é uma mensagem do seu subconsciente. Simboliza **UNTAMED NATURE**.",
  "symbolism": "O símbolo **Wolf** conecta seu consciente com o inconsciente.",
  "cosmicAnalysis": "Sonhos com Wolf estão profundamente ligados ao ciclo lunar. Durante a **Lua Crescente**, este símbolo sugere crescimento.",
  "commonScenarios": [
    "**Ver um Wolf:** Um sinal importante."
  ],
  "cta": "Baixe **Dream Boat** para mais."
}