{
  "slug": "being-ignored",
  "localizedName": "Being Ignored",
  "title": "Dreaming of Being Ignored",
  "description": "Dreaming of being ignored can be a reflection of feelings of neglect or worthlessness.",
  "meanings": [
    {
      "title": "Main Interpretation",
      "description": "According to Freud and Jung, a dream of being ignored may reflect anxieties about not being accepted or feared rejection in waking life."
    },
    {
      "title": "Subconscious Warning",
      "description": "Your subconscious might be indicating that you need to voice your opinions or get noticed in significant areas."
    },
    {
      "title": "Life Context",
      "description": "This scenario could be linked to feelings of exclusion or worthlessness in social relationships in daily life."
    }
  ],
  "symbolism": {
    "concepts": [
      "Rejection",
      "Loneliness"
    ],
    "elements": [
      "Darkness",
      "Silence"
    ]
  },
  "interpretation": "Such dreams may reflect one's desire for acceptance within their social circle and the disappointment from failing to achieve it.",
  "context": {
    "positive": "This dream may prompt you to enhance your social skills and communication abilities.",
    "negative": "The dream might indicate issues like low self-esteem or social anxiety."
  },
  "keywords": [
    "Being Ignored",
    "Birinin seni görmezden gelmesi",
    "neglect",
    "worthlessness"
  ]
}